npfc/__init__.py
npfc/deduplicate.py
npfc/draw.py
npfc/duplicate.py
npfc/filter.py
npfc/fragment_combination.py
npfc/fragment_combination_graph.py
npfc/fragment_combination_point.py
npfc/fragment_search.py
npfc/load.py
npfc/notebook.py
npfc/report.py
npfc/save.py
npfc/standardize.py
npfc/utils.py
npfc/__pycache__/__init__.cpython-310.pyc
npfc/__pycache__/__init__.cpython-39.pyc
npfc/__pycache__/deduplicate.cpython-310.pyc
npfc/__pycache__/deduplicate.cpython-39.pyc
npfc/__pycache__/draw.cpython-310.pyc
npfc/__pycache__/draw.cpython-39.pyc
npfc/__pycache__/filter.cpython-310.pyc
npfc/__pycache__/filter.cpython-39.pyc
npfc/__pycache__/fragment_combination.cpython-310.pyc
npfc/__pycache__/fragment_combination.cpython-39.pyc
npfc/__pycache__/fragment_combination_graph.cpython-310.pyc
npfc/__pycache__/fragment_combination_graph.cpython-39.pyc
npfc/__pycache__/fragment_combination_point.cpython-310.pyc
npfc/__pycache__/fragment_combination_point.cpython-39.pyc
npfc/__pycache__/fragment_search.cpython-310.pyc
npfc/__pycache__/fragment_search.cpython-39.pyc
npfc/__pycache__/load.cpython-310.pyc
npfc/__pycache__/load.cpython-39.pyc
npfc/__pycache__/notebook.cpython-310.pyc
npfc/__pycache__/notebook.cpython-39.pyc
npfc/__pycache__/report.cpython-310.pyc
npfc/__pycache__/report.cpython-39.pyc
npfc/__pycache__/save.cpython-310.pyc
npfc/__pycache__/save.cpython-39.pyc
npfc/__pycache__/standardize.cpython-310.pyc
npfc/__pycache__/standardize.cpython-39.pyc
npfc/__pycache__/utils.cpython-310.pyc
npfc/__pycache__/utils.cpython-39.pyc
npfc/contrib/__init__.py
npfc/contrib/np_score.py
npfc/contrib/sa_score.py
npfc/data/cluster_clem.json
npfc/data/cluster_gwdg1.json
npfc/data/fragments.json
npfc/data/fragments_old.smk
npfc/data/model_np_score.model.gz
npfc/data/model_sa_score.pkl.gz
npfc/data/natural.json
npfc/data/report.mplstyle
npfc/data/std_fragments.json
npfc/data/std_mols.json
npfc/data/synthetic.json
npfc/data/fc/__fc_fragments_tmp.smk
npfc/data/fc/fc_commercial.smk
npfc-0.7.21.dist-info/LICENSE
npfc-0.7.21.dist-info/METADATA
npfc-0.7.21.dist-info/WHEEL
npfc-0.7.21.dist-info/top_level.txt
npfc-0.7.21.dist-info/RECORD
