Metadata-Version: 2.1
Name: npfc
Version: 0.7.21
Summary: A tool for describing Natural Product- (NP) fragments combinations and identifying pseudo-NPs.
Home-page: https://github.com/jose-manuel/npfc
Author: Jose-Manuel Gally
Author-email: josemanuel.gally@mpi-dortmund.mpg.de
Keywords: chemical biology,pseudo-natural products,computational chemistry,natural products,fragments
Classifier: Programming Language :: Python :: 3
Classifier: License :: OSI Approved :: MIT License
Classifier: Operating System :: OS Independent
License-File: LICENSE
Requires-Dist: adjustText (>=0.7.3)
Requires-Dist: networkx (>=2.6)
Requires-Dist: ipython (>=7.25)
Requires-Dist: more-itertools (>=8.8)
Requires-Dist: pandas (>=1.1.4)
Requires-Dist: pillow (>=8.3.1)
Requires-Dist: psycopg2-binary (>=2.9)
Requires-Dist: rdkit-pypi (>=2021.03)
Requires-Dist: snakemake (>=5.0)
Requires-Dist: seaborn (>=0.11)
Requires-Dist: toolz (>=0.11)
Requires-Dist: scipy (>=1.5)
Requires-Dist: isort (>=4.3)
Requires-Dist: pylint (>=2.4)
Requires-Dist: pytest (>=6.2)
Requires-Dist: sphinx (>=3.0)
Requires-Dist: sphinx-autodoc-typehints (>=1.10)
Requires-Dist: recommonmark
Requires-Dist: sphinx-rtd-theme (>=0.4)
Requires-Dist: twine (>=3.4)
Requires-Dist: wheel (>=0.36)
